Booths Multiplier/src/controller.v
//-----------------------------------------------------------------------------
//
// Title       : controller
// Design      : Booths Multiplier
// Author      : donieltripura1971@gmail.com
// Company     : Machang
//
//-----------------------------------------------------------------------------
//
// File        : f:/Academic/4th Year/8th Semester/dsd/Booths_Multiplier/Booths Multiplier/src/controller.v
// Generated   : Mon Nov 25 14:54:08 2024
// From        : Interface description file
// By          : ItfToHdl ver. 1.0
//
//-----------------------------------------------------------------------------
//
// Description : 
//
//-----------------------------------------------------------------------------

`timescale 1ps / 1ps

//{{ Section below this comment is automatically maintained
//    and may be overwritten
//{module {controller}}

module controller(ldA,clrA,sftA,ldQ,clrQ,sftQ,ldM,clrFF,addsub,start,decr,
                     ldcount,done,clk,q0,qm1,eqz);
					 
    input clk,q0,qm1,start,eqz;
	output  ldA,clrA,sftA,ldQ,clrQ,sftQ,ldM,clrFF,addsub,decr,
                     ldcount,done;

	reg [2:0] state;
    parameter [2:0] S0 = 3'b000,
                    S1 = 3'b001,
					S2 = 3'b010,
					S3 = 3'b011,
					S4 = 3'b100,
					S5 = 3'b101,
					S6 = 3'b110;
					
	always@(posedge clk)
       begin
	        case(state)
			   S0 :  state = start?S1:S0;
			   S1 :  state = S2;
			   S2 :  begin
                     #1
			         if({q0,qm1}==2'b01)
					    state =  S3;
				     else if({q0,qm1}==2'b10)
					    state =  S4;
				     else if(({q0,qm1}==2'b00)||({q0,qm1}==2'b11))	
                        state =  S5;					 
                     end
					 
				S3 :  state =  S5;
				S4 :  state =  S5;
				S5 :  begin
                         #1 
				          if(({q0,qm1}==2'b01) && !eqz)
					         state =  S3;
				          else if(({q0,qm1}==2'b10) && !eqz)
							 state =  S4;
						  else if(eqz)
						     state = S6;    
				      end
				S6 :  state = S6;
				default : state <= S0;
			endcase	
		end	   
				
 
  
    assign ldA     = ((state == S3)||(state == S4))?1:0;
    assign clrA    =  (state == S0)?1:0;
	assign sftA    =  (state == S5)?1:0;
    assign ldQ     =  (state == S2)?1:0;
    assign clrQ    =  (state == S0)?1:0;
	assign sftQ    =  (state == S5)?1:0;
    assign ldM     =  (state == S1)?1:0;
    assign clrFF   =  (state == S0)?1:0;
	assign addsub     =  (state == S3)?1:0;
    
	assign decr    =  (state == S5)?1:0;
	assign ldcount =  (state == S1)?1:0; 
	assign done    =  (state == S6)?1:0;	

//}} End of automatically maintained section

// Enter your statements here //

endmodule

Booths Multiplier/src/bitcounter.v
//-----------------------------------------------------------------------------
//
// Title       : bitcounter
// Design      : Booths Multiplier
// Author      : donieltripura1971@gmail.com
// Company     : Machang
//
//-----------------------------------------------------------------------------
//
// File        : f:/Academic/4th Year/8th Semester/dsd/Booths_Multiplier/Booths Multiplier/src/bitcounter.v
// Generated   : Mon Nov 25 14:52:51 2024
// From        : Interface description file
// By          : ItfToHdl ver. 1.0
//
//-----------------------------------------------------------------------------
//
// Description : 
//
//-----------------------------------------------------------------------------

`timescale 1ps / 1ps

//{{ Section below this comment is automatically maintained
//    and may be overwritten
//{module {bitcounter}}

module bitcounter(countdata,decr,ldcount,clk);
     input decr,ldcount,clk;
	 output reg [4:0] countdata;
	 
	 always@(posedge clk)
	   begin
	       if(ldcount)
		      countdata <= 16; //since datain is of 16 bits width
		   else if(decr)
              countdata <= countdata - 1;			
	   end

//}} End of automatically maintained section

// Enter your statements here //

endmodule

Booths Multiplier/src/ALU.v
//-----------------------------------------------------------------------------
//
// Title       : ALU
// Design      : Booths Multiplier
// Author      : donieltripura1971@gmail.com
// Company     : Machang
//
//-----------------------------------------------------------------------------
//
// File        : f:/Academic/4th Year/8th Semester/dsd/Booths_Multiplier/Booths Multiplier/src/ALU.v
// Generated   : Mon Nov 25 14:51:51 2024
// From        : Interface description file
// By          : ItfToHdl ver. 1.0
//
//-----------------------------------------------------------------------------
//
// Description : 
//
//-----------------------------------------------------------------------------

`timescale 1ps / 1ps

//{{ Section below this comment is automatically maintained
//    and may be overwritten
//{module {ALU}}

module ALU (out,in1,in2,addsub);

  input addsub ;  // addsub = 1 then addition else subtraction
  input signed[15:0] in1,in2;
  output reg signed[15:0] out;
  
  always@(*)
    begin
      if(addsub)
	      out  = in1 + in2;
      else if(!addsub)
	      out  = in1 - in2;
	end

//}} End of automatically maintained section

// Enter your statements here //

endmodule

Booths Multiplier/src/PIPO.v
//-----------------------------------------------------------------------------
//
// Title       : PIPO
// Design      : Booths Multiplier
// Author      : donieltripura1971@gmail.com
// Company     : Machang
//
//-----------------------------------------------------------------------------
//
// File        : f:/Academic/4th Year/8th Semester/dsd/Booths_Multiplier/Booths Multiplier/src/PIPO.v
// Generated   : Mon Nov 25 14:52:24 2024
// From        : Interface description file
// By          : ItfToHdl ver. 1.0
//
//-----------------------------------------------------------------------------
//
// Description : 
//
//-----------------------------------------------------------------------------

`timescale 1ps / 1ps

//{{ Section below this comment is automatically maintained
//    and may be overwritten
//{module {PIPO}}

module PIPO(data_out,data_in,clk,ld);

input signed [15:0] data_in;
input clk,ld;
output reg signed [15:0] data_out;

always@(posedge clk)
  begin
      if(ld)
        data_out <= data_in;
   end

//}} End of automatically maintained section

// Enter your statements here //

endmodule

Booths Multiplier/src/dflipflop.v
//-----------------------------------------------------------------------------
//
// Title       : dflipflop
// Design      : Booths Multiplier
// Author      : donieltripura1971@gmail.com
// Company     : Machang
//
//-----------------------------------------------------------------------------
//
// File        : f:/Academic/4th Year/8th Semester/dsd/Booths_Multiplier/Booths Multiplier/src/dflipflop.v
// Generated   : Mon Nov 25 14:54:33 2024
// From        : Interface description file
// By          : ItfToHdl ver. 1.0
//
//-----------------------------------------------------------------------------
//
// Description : 
//
//-----------------------------------------------------------------------------

`timescale 1ps / 1ps

//{{ Section below this comment is automatically maintained
//    and may be overwritten
//{module {dflipflop}}

module dflipflop(data_in,clk,rst,data_out);

input data_in,clk,rst;
output reg data_out;

always@(posedge clk)
   begin
        if(rst)
		   data_out <= 0;
		else 
		   data_out <= data_in;
   end

//}} End of automatically maintained section

// Enter your statements here //

endmodule

Booths Multiplier/src/shiftreg.v
//-----------------------------------------------------------------------------
//
// Title       : shiftreg
// Design      : Booths Multiplier
// Author      : donieltripura1971@gmail.com
// Company     : Machang
//
//-----------------------------------------------------------------------------
//
// File        : f:/Academic/4th Year/8th Semester/dsd/Booths_Multiplier/Booths Multiplier/src/shiftreg.v
// Generated   : Mon Nov 25 14:55:02 2024
// From        : Interface description file
// By          : ItfToHdl ver. 1.0
//
//-----------------------------------------------------------------------------
//
// Description : 
//
//-----------------------------------------------------------------------------

`timescale 1ps / 1ps

//{{ Section below this comment is automatically maintained
//    and may be overwritten
//{module {shiftreg}}

module shiftreg(data_out,ld_data,s_in,clk,ld,rst,sft);   //SIPO

input [15:0] ld_data;
input clk,rst,ld,s_in,sft;
output reg [15:0]data_out;

always@(posedge clk)
 begin
    if(rst)
	    data_out <= 0;
	else if(ld)
        data_out <= ld_data;
    else if(sft)
        data_out <= {s_in,data_out[15:1]};	
 end

//}} End of automatically maintained section

// Enter your statements here //

endmodule

Booths Multiplier/src/boothmultiplier.v
//-----------------------------------------------------------------------------
//
// Title       : boothmultiplier
// Design      : Booths Multiplier
// Author      : donieltripura1971@gmail.com
// Company     : Machang
//
//-----------------------------------------------------------------------------
//
// File        : f:/Academic/4th Year/8th Semester/dsd/Booths_Multiplier/Booths Multiplier/src/boothmultiplier.v
// Generated   : Mon Nov 25 14:53:15 2024
// From        : Interface description file
// By          : ItfToHdl ver. 1.0
//
//-----------------------------------------------------------------------------
//
// Description : 
//
//-----------------------------------------------------------------------------

`timescale 1ps / 1ps

//{{ Section below this comment is automatically maintained
//    and may be overwritten
//{module {boothmultiplier}}

module boothmultiplier(data_in,clk,start,result);
	
  wire ldA,clrA,sftA,ldQ,clrQ,sftQ,done;
  wire ldM,clrFF,addsub,decr,ldcount;
  input signed [15:0]data_in;
  input start,clk;
  wire qm1,eqz;
    output signed [31:0]result;
  wire [4:0] countdata;
  wire signed [15:0] A,M,Q,Z;   //A->Acc , M->Multiplicand , Q->Multiplier, Z->(A-M,A+M) 
  assign eqz = ~| (countdata);
    assign result = {A,Q};

  shiftreg Acc_A(.data_out(A),
                 .ld_data(Z),
				 .s_in(A[15]),
				 .clk(clk),
				 .ld(ldA),
				 .rst(clrA),
				 .sft(sftA));
  
  
  
  shiftreg Mlpr_Q(.data_out(Q),
                .ld_data(data_in),
				.s_in(A[0]),
				.clk(clk),
				.ld(ldQ),
				.rst(clrQ),
				.sft(sftQ));
				
				
   dflipflop d_ff(.data_in(Q[0]),
                  .clk(clk),
				  .rst(clrFF),
				  .data_out(qm1));
				  
	
    PIPO Mlcd_M(.data_out(M),
                .data_in(data_in),
				.clk(clk),
				.ld(ldM));
				
	ALU  Adsub(.out(Z),
	           .in1(A),
			   .in2(M),
               .addsub(addsub));			
				
    bitcounter counter(.countdata(countdata),
	                   .decr(decr),
					   .ldcount(ldcount),
					   .clk(clk));
    
	controller fsm(.ldA(ldA),
	               .clrA(clrA),
				   .sftA(sftA),
				   .ldQ(ldQ),
				   .clrQ(clrQ),
				   .sftQ(sftQ),
				   .ldM(ldM),
				   .clrFF(clrFF),
                   .addsub(addsub),
				   .start(start),
				   .decr(decr),
				   .ldcount(ldcount),
				   .done(done),
				   .clk(clk),
				   .q0(Q[0]),
				   .qm1(qm1),
				   .eqz(eqz)); 

//}} End of automatically maintained section

// Enter your statements here //

endmodule

Booths Multiplier/src/boothmultiplier_tb.v
//-----------------------------------------------------------------------------
//
// Title       : boothmultiplier_tb
// Design      : Booths Multiplier
// Author      : donieltripura1971@gmail.com
// Company     : Machang
//
//-----------------------------------------------------------------------------
//
// File        : f:/Academic/4th Year/8th Semester/dsd/Booths_Multiplier/Booths Multiplier/src/boothmultiplier_tb.v
// Generated   : Mon Nov 25 14:53:40 2024
// From        : Interface description file
// By          : ItfToHdl ver. 1.0
//
//-----------------------------------------------------------------------------
//
// Description : 
//
//-----------------------------------------------------------------------------

`timescale 10ps / 1ps

//{{ Section below this comment is automatically maintained
//    and may be overwritten
//{module {boothmultiplier_tb}}

module boothmultiplier_tb();
  reg [15:0] data_in;
  reg clk,start;
  wire [31:0] result;
  
  boothmultiplier dut(data_in,clk,start,result);
  
  initial
     begin
       clk = 0;
       forever #5 clk = ~clk;
     end
  
   
    
  initial
      begin
        
       
        @(negedge clk) start = 1;
        @(negedge clk) data_in = 10;
        @(negedge clk) data_in = 13;
   
        #500 $finish;
     end
  
    initial
      begin
        $dumpfile("boothmultiplier_tb.vcd");
        $dumpvars;
      
      end

//}} End of automatically maintained section

// Enter your statements here //

endmodule

Booths Multiplier/boothmultiplier_tb.vcd
$date
Mon Nov 25 14:59:17 2024
$end
$version
Aldec HDL Simulator Version 15.0.261
$end
$timescale
1 ps
$end

$scope module boothmultiplier_tb $end
$var wire 32 ! result [31:0] $end
$var reg 16 " data_in [15:0] $end
$var reg 1 # clk $end
$var reg 1 $ start $end

$scope module dut $end

$scope module Acc_A $end
$var reg 16 % data_out [15:0] $end
$upscope $end


$scope module Mlpr_Q $end
$var reg 16 & data_out [15:0] $end
$upscope $end


$scope module d_ff $end
$var reg 1 ' data_out $end
$upscope $end


$scope module Mlcd_M $end
$var reg 16 ( data_out [15:0] $end
$upscope $end


$scope module Adsub $end
$var reg 16 ) out [15:0] $end
$upscope $end


$scope module counter $end
$var reg 5 * countdata [4:0] $end
$upscope $end


$scope module fsm $end
$var reg 3 + state [2:0] $end
$var parameter 3 , S0 [2:0] $end
$var parameter 3 - S1 [2:0] $end
$var parameter 3 . S2 [2:0] $end
$var parameter 3 / S3 [2:0] $end
$var parameter 3 0 S4 [2:0] $end
$var parameter 3 1 S5 [2:0] $end
$var parameter 3 2 S6 [2:0] $end
$upscope $end

$upscope $end

$upscope $end

$enddefinitions $end
$dumpvars
bx !
bx "
0#
x$
b0 ,
b1 -
b10 .
b11 /
b100 0
b101 1
b110 2
$end
#50
1#
#100
0#
1$
#150
1#
b0 !
#200
0#
b1010 "
#250
1#
#300
0#
b1101 "
#350
1#
b1101 !
#400
0#
#450
1#
b11111111111101100000000000001101 !
#500
0#
#550
1#
b11111111111110110000000000000110 !
#600
0#
#650
1#
b1010000000000000110 !
#700
0#
#750
1#
b101000000000000011 !
#800
0#
#850
1#
b11111111111110001000000000000011 !
#900
0#
#950
1#
b11111111111111000100000000000001 !
#1000
0#
#1050
1#
b11111111111111100010000000000000 !
#1100
0#
#1150
1#
b10000010000000000000 !
#1200
0#
#1250
1#
b1000001000000000000 !
#1300
0#
#1350
1#
b100000100000000000 !
#1400
0#
#1450
1#
b10000010000000000 !
#1500
0#
#1550
1#
b1000001000000000 !
#1600
0#
#1650
1#
b100000100000000 !
#1700
0#
#1750
1#
b10000010000000 !
#1800
0#
#1850
1#
b1000001000000 !
#1900
0#
#1950
1#
b100000100000 !
#2000
0#
#2050
1#
b10000010000 !
#2100
0#
#2150
1#
b1000001000 !
#2200
0#
#2250
1#
b100000100 !
#2300
0#
#2350
1#
b10000010 !
